odoo/addons/l10n_fr_das2/README.rst
odoo/addons/l10n_fr_das2/__init__.py
odoo/addons/l10n_fr_das2/__manifest__.py
odoo/addons/l10n_fr_das2/demo/demo.xml
odoo/addons/l10n_fr_das2/i18n/l10n_fr_das2.pot
odoo/addons/l10n_fr_das2/models/__init__.py
odoo/addons/l10n_fr_das2/models/company.py
odoo/addons/l10n_fr_das2/models/config_settings.py
odoo/addons/l10n_fr_das2/models/l10n_fr_das2.py
odoo/addons/l10n_fr_das2/models/partner.py
odoo/addons/l10n_fr_das2/readme/CONFIGURE.rst
odoo/addons/l10n_fr_das2/readme/CONTRIBUTORS.rst
odoo/addons/l10n_fr_das2/readme/DESCRIPTION.rst
odoo/addons/l10n_fr_das2/readme/USAGE.rst
odoo/addons/l10n_fr_das2/security/das2_security.xml
odoo/addons/l10n_fr_das2/security/ir.model.access.csv
odoo/addons/l10n_fr_das2/static/description/icon.png
odoo/addons/l10n_fr_das2/static/description/index.html
odoo/addons/l10n_fr_das2/views/config_settings.xml
odoo/addons/l10n_fr_das2/views/l10n_fr_das2.xml
odoo/addons/l10n_fr_das2/views/partner.xml
odoo12_addon_l10n_fr_das2-12.0.1.0.1.dist-info/METADATA
odoo12_addon_l10n_fr_das2-12.0.1.0.1.dist-info/WHEEL
odoo12_addon_l10n_fr_das2-12.0.1.0.1.dist-info/top_level.txt
odoo12_addon_l10n_fr_das2-12.0.1.0.1.dist-info/RECORD
